frameMerge/__init__.py
frameMerge/helpers.py
frameMerge/main.py
frameMerge/merger.py
framemerge-1.1.0.dist-info/licenses/LICENSE
framemerge-1.1.0.dist-info/METADATA
framemerge-1.1.0.dist-info/WHEEL
framemerge-1.1.0.dist-info/entry_points.txt
framemerge-1.1.0.dist-info/top_level.txt
framemerge-1.1.0.dist-info/RECORD
