Metadata-Version: 2.4
Name: frameMerge
Version: 1.1.0
Summary: Lightweight tool to merge crystallographic frames
Author-email: Ryan ODea <ryan.odea@psi.ch>
Maintainer-email: Ryan ODea <ryan.odea@psi.ch>
License-Expression: MIT
Project-URL: Repository, https://github.com/ryan-odea/frameMerge
Keywords: crystallography,data processing
Requires-Python: >=3.8
License-File: LICENSE
Requires-Dist: h5py>=3.0.0
Requires-Dist: bitshuffle>=0.3.0
Requires-Dist: numpy>=1.20.0
Dynamic: license-file
